docktgrid/__init__.py
docktgrid/config.py
docktgrid/grid.py
docktgrid/molecule.py
docktgrid/molparser.py
docktgrid/periodictable.py
docktgrid/transforms.py
docktgrid/view.py
docktgrid/voxel.py
docktgrid/voxel_dataset.py
docktgrid-0.0.3.dist-info/licenses/COPYING.LESSER
docktgrid-0.0.3.dist-info/METADATA
docktgrid-0.0.3.dist-info/WHEEL
docktgrid-0.0.3.dist-info/top_level.txt
docktgrid-0.0.3.dist-info/RECORD
