Metadata-Version: 2.4
Name: docktgrid
Version: 0.0.3
Summary: Create customized voxel representations of protein-ligand complexes using GPU.
Author-email: Matheus Müller Pereira da Silva <matheusp@posgrad.lncc.br>
License: LGPL-3.0-only
Project-URL: Homepage, https://github.com/gmmsb-lncc/docktgrid
Keywords: voxel-grid,deep-learning,molecular-docking,virtual-screening
Classifier: License :: OSI Approved :: GNU Lesser General Public License v3 (LGPLv3)
Classifier: Programming Language :: Python
Classifier: Programming Language :: Python :: 3
Classifier: Environment :: GPU
Classifier: Topic :: Scientific/Engineering
Classifier: Topic :: Scientific/Engineering :: Chemistry
Classifier: Topic :: Scientific/Engineering :: Bio-Informatics
Classifier: Topic :: Scientific/Engineering :: Artificial Intelligence
Requires-Python: >=3.8
License-File: COPYING.LESSER
Requires-Dist: torch<3.0.0
Requires-Dist: biopandas<1.0.0,>=0.4.1
Requires-Dist: scipy<3.0.0
Requires-Dist: numpy<3.0.0
Provides-Extra: dev
Requires-Dist: black; extra == "dev"
Requires-Dist: pytest; extra == "dev"
Dynamic: license-file
